[
    {
        "path": "result/raw_result/resnet152_posLen_tp_1_lw_hlr/tests/posLen_tp_1/Iter_112000/resultInfo.json",
        "loss": {
            "MLAE": {
                "avg": -2.27897056079521,
                "std": 0.20768672752587977
            },
            "MLAE_unmatch": {
                "avg": -3.0,
                "std": 0.0
            },
            "ABS": {
                "avg": 0.0008322436944332779,
                "std": 0.0003071632683654746
            },
            "ABS_unmatch": {
                "avg": 0.0,
                "std": 0.0
            },
            "count": 10000
        }
    }
]